pylogpresso/__init__.py
pylogpresso/client.py
pylogpresso/console.py
pylogpresso/query.py
pylogpresso/session.py
pylogpresso/websocket.py
pylogpresso-0.1.1.dist-info/LICENSE
pylogpresso-0.1.1.dist-info/METADATA
pylogpresso-0.1.1.dist-info/WHEEL
pylogpresso-0.1.1.dist-info/top_level.txt
pylogpresso-0.1.1.dist-info/RECORD
