Metadata-Version: 2.1
Name: pylogpresso
Version: 0.1.1
Summary: Python client library for logpresso
Home-page: https://github.com/logpresso/pylogpresso
Author: Logpresso
Author-email: support@logpresso.com
License: Apache Software License 2
Platform: UNKNOWN
Classifier: Programming Language :: Python :: 3
Classifier: Operating System :: OS Independent
